{
  "Map": [
    {
      "Name": "./SampleData/models/传感器设备/传感器设备_data/GELH100.gltf",
      "Position": "-66.9168464996479,-583.014278227973,-37.0968291046916",
      "Matrix": "1,0,0,0,1,0,0,0,1"
    },   
    {
      "Name": "./SampleData/models/传感器设备/传感器设备_data/GFW15.gltf",
      "Position": "-88.96997456194,-574.589912923564,-37.4303611882814",
      "Matrix": "1,0,0,0,1,0,0,0,1"
    },
    {
      "Name": "./SampleData/models/传感器设备/传感器设备_data/GFW15.gltf",
      "Position": "-90.8108553201295,-576.191618371897,-37.3823870507033",
      "Matrix": "1,0,0,0,1,0,0,0,1"
    },
    {
      "Name": "./SampleData/models/传感器设备/传感器设备_data/GFY15.gltf",
      "Position": "-101.027289237426,-573.504588341725,-36.877471037305",
      "Matrix": "1,0,0,0,1,0,0,0,1"
    },
    {
      "Name": "./SampleData/models/传感器设备/传感器设备_data/GFY15.gltf",
      "Position": "-103.237897555476,-571.162854328656,-36.7944813066018",
      "Matrix": "1,0,0,0,1,0,0,0,1"
    },
    {
      "Name": "./SampleData/models/传感器设备/传感器设备_data/GFY15.gltf",
      "Position": "-105.088267780622,-569.264694462134,-36.7200372495364",
      "Matrix": "1,0,0,0,1,0,0,0,1"
    },
    {
      "Name": "./SampleData/models/传感器设备/传感器设备_data/GFY15.gltf",
      "Position": "-107.797783737632,-566.210886518952,-36.6328860250318",
      "Matrix": "1,0,0,0,1,0,0,0,1"
    },
    {
      "Name": "./SampleData/models/传感器设备/传感器设备_data/GFY15.gltf",
      "Position": "-109.698841068286,-563.517844696995,-36.5549834282065",
      "Matrix": "1,0,0,0,1,0,0,0,1"
    },
    {
      "Name": "./SampleData/models/传感器设备/传感器设备_data/GFY15.gltf",
      "Position": "-111.733474235182,-560.739121719197,-36.5897862970222",
      "Matrix": "1,0,0,0,1,0,0,0,1"
    },
    {
      "Name": "./SampleData/models/传感器设备/传感器设备_data/GFY15.gltf",
      "Position": "-115.939069968138,-556.112980763146,-36.4458566734148",
      "Matrix": "1,0,0,0,1,0,0,0,1"
    },
    {
      "Name": "./SampleData/models/传感器设备/传感器设备_data/GFY15.gltf",
      "Position": "-126.022586727135,-545.316799255302,-36.0766077789416",
      "Matrix": "1,0,0,0,1,0,0,0,1"
    },
    {
      "Name": "./SampleData/models/传感器设备/传感器设备_data/GJ440.gltf",
      "Position": "-150.557058237214,-517.425638455806,-35.9941614181405",
      "Matrix": "1,0,0,0,1,0,0,0,1"
    },
    {
      "Name": "./SampleData/models/传感器设备/传感器设备_data/GJ440.gltf",
      "Position": "-161.260496205216,-506.249378821538,-35.9284740039797",
      "Matrix": "0.7808688,0.6246951,0,-0.6246951,0.7808688,0,0,0,1"
    },
    {
      "Name": "./SampleData/models/传感器设备/传感器设备_data/GJ440.gltf",
      "Position": "-180.526287606386,-484.427666316391,-35.9755841385968",
      "Matrix": "1,0,0,0,1,0,0,0,1"
    },
    {
      "Name": "./SampleData/models/传感器设备/传感器设备_data/GLH100.gltf",
      "Position": "-190.340283969036,-473.591765383478,-35.9724588298305",
      "Matrix": "1,0,0,0,1,0,0,0,1"
    },
    {
      "Name": "./SampleData/models/传感器设备/传感器设备_data/GLH100.gltf",
      "Position": "-197.736877186312,-466.161638978193,-35.8985595209597",
      "Matrix": "0.9486833,0.3162278,0,-0.3162278,0.9486833,0,0,0,1"
    },    
    {
      "Name": "./SampleData/models/传感器设备/传感器设备_data/GRG5H(B).gltf",
      "Position": "-67.6670464131503,-553.056939213925,-36.6664636540183",
      "Matrix": "1,0,0,0,1,0,0,0,1"
    },
    {
      "Name": "./SampleData/models/传感器设备/传感器设备_data/GRG5H(B).gltf",
      "Position": "-66.1195937072964,-551.85970181989,-36.7724130171679",
      "Matrix": "1,0,0,0,1,0,0,0,1"
    },
    {
      "Name": "./SampleData/models/传感器设备/传感器设备_data/GRG5H(B).gltf",
      "Position": "-63.7598616514351,-549.724132309718,-36.7976134093492",
      "Matrix": "1,0,0,0,1,0,0,0,1"
    },
    {
      "Name": "./SampleData/models/传感器设备/传感器设备_data/GRG5H(B).gltf",
      "Position": "-62.2116576993981,-547.91078147557,-36.6327530587811",
      "Matrix": "0.9977852,-0.06651901,0,0.06651901,0.9977852,0,0,0,1"
    },
    {
      "Name": "./SampleData/models/传感器设备/传感器设备_data/GRG5H(B).gltf",
      "Position": "-60.0627793335553,-545.256077703925,-36.3432890722877",
      "Matrix": "0.9899495,0.1414214,0,-0.1414214,0.9899495,0,0,0,1"
    },
    {
      "Name": "./SampleData/models/传感器设备/传感器设备_data/GRG5H(B).gltf",
      "Position": "-56.4152486640808,-539.520272610153,-35.8047227425265",
      "Matrix": "1,0,0,0,1,0,0,0,1"
    },
    {
      "Name": "./SampleData/models/传感器设备/传感器设备_data/GFY15.gltf",
      "Position": "-53.8952254209275,-539.631357066044,-36.3902093071994",
      "Matrix": "1,0,0,0,1,0,0,0,1"
    },
    {
      "Name": "./SampleData/models/传感器设备/传感器设备_data/GFY15.gltf",
      "Position": "-51.7182782129394,-537.491331288688,-36.3387041392991",
      "Matrix": "1,0,0,0,1,0,0,0,1"
    },
    {
      "Name": "./SampleData/models/传感器设备/传感器设备_data/GFY15.gltf",
      "Position": "-50.7015069512025,-536.44358172107,-36.293427781341",
      "Matrix": "1,0,0,0,1,0,0,0,1"
    },
    {
      "Name": "./SampleData/models/传感器设备/传感器设备_data/GSY10.gltf",
      "Position": "-107.891496746221,-443.888314985674,-50",
      "Matrix": "1,0,0,0,1,0,0,0,1"
    },
    {
      "Name": "./SampleData/models/传感器设备/传感器设备_data/GSY10.gltf",
      "Position": "-81.6342054943859,-594.343156018916,-37.1772901742677",
      "Matrix": "-0.3417431,-0.9397934,0,0.9397934,-0.3417431,0,0,0,1"
    },
    {
      "Name": "./SampleData/models/传感器设备/传感器设备_data/GSY10.gltf",
      "Position": "-80.613789191256,-595.438212497172,-37.1811625154737",
      "Matrix": "1,0,0,0,1,0,0,0,1"
    },
    {
      "Name": "./SampleData/models/传感器设备/传感器设备_data/GSY10.gltf",
      "Position": "-80.7692738403719,-595.62655602855,-37.1423234532407",
      "Matrix": "1,0,0,0,1,0,0,0,1"
    },
    {
      "Name": "./SampleData/models/传感器设备/传感器设备_data/GTH1000.gltf",
      "Position": "-96.9532784361444,-582.497818398316,-37.4350411631124",
      "Matrix": "1,0,0,0,1,0,0,0,1"
    },
    {
      "Name": "./SampleData/models/传感器设备/传感器设备_data/GTH1000.gltf",
      "Position": "-98.3332970740526,-583.84252823235,-37.3406210704607",
      "Matrix": "-0.8574929,-0.5144957,0,0.5144957,-0.8574929,0,0,0,1"
    },
    {
      "Name": "./SampleData/models/传感器设备/传感器设备_data/GTH1000.gltf",
      "Position": "-99.4956923847807,-585.270799003123,-37.3779322142083",
      "Matrix": "1,0,0,0,1,0,0,0,1"
    },
    {
      "Name": "./SampleData/models/传感器设备/传感器设备_data/GTH1000.gltf",
      "Position": "-100.725727907982,-586.68874533777,-37.3804613881203",
      "Matrix": "1,0,0,0,1,0,0,0,1"
    },
    {
      "Name": "./SampleData/models/传感器设备/传感器设备_data/GTH1000.gltf",
      "Position": "-102.03245159984,-588.033563261658,-37.319262375516",
      "Matrix": "1,0,0,0,1,0,0,0,1"
    },
    {
      "Name": "./SampleData/models/传感器设备/传感器设备_data/GTH1000G.gltf",
      "Position": "-103.066293689922,-588.966815429828,-37.219140102792",
      "Matrix": "1,0,0,0,1,0,0,0,1"
    },
    {
      "Name": "./SampleData/models/传感器设备/传感器设备_data/GTH1000G.gltf",
      "Position": "-103.597041782853,-589.191680611492,-37.0671868007001",
      "Matrix": "1,0,0,0,1,0,0,0,1"
    },
    {
      "Name": "./SampleData/models/传感器设备/传感器设备_data/GTH1000G.gltf",
      "Position": "-104.396749208893,-590.043496868559,-37.0411219423226",
      "Matrix": "1,0,0,0,1,0,0,0,1"
    },
    {
      "Name": "./SampleData/models/传感器设备/传感器设备_data/GTH1000G.gltf",
      "Position": "-119.537582200921,-575.992888478356,-37.1645994610019",
      "Matrix": "1,0,0,0,1,0,0,0,1"
    },
    {
      "Name": "./SampleData/models/传感器设备/传感器设备_data/GTH1000G.gltf",
      "Position": "-115.986264752398,-572.102772658099,-36.9049155583668",
      "Matrix": "1,0,0,0,1,0,0,0,1"
    },
    {
      "Name": "./SampleData/models/传感器设备/传感器设备_data/GWD100.gltf",
      "Position": "-117.384078011701,-526.701220328683,-36.1065653790944",
      "Matrix": "1,0,0,0,1,0,0,0,1"
    },
    {
      "Name": "./SampleData/models/传感器设备/传感器设备_data/GWD100.gltf",
      "Position": "-119.449364534757,-523.940789784604,-36.015191527221",
      "Matrix": "1,0,0,0,1,0,0,0,1"
    },
    {
      "Name": "./SampleData/models/传感器设备/传感器设备_data/GWD100.gltf",
      "Position": "-125.837232872808,-516.242138257772,-35.8838588748166",
      "Matrix": "1,0,0,0,1,0,0,0,1"
    },
    {
      "Name": "./SampleData/models/传感器设备/传感器设备_data/GWD100.gltf",
      "Position": "-129.087215523791,-512.544848184079,-35.8251839558083",
      "Matrix": "1,0,0,0,1,0,0,0,1"
    },
    {
      "Name": "./SampleData/models/传感器设备/传感器设备_data/GWD100.gltf",
      "Position": "-134.036881865152,-508.249270268503,-35.7876765993239",
      "Matrix": "1,0,0,0,1,0,0,0,1"
    },
    {
      "Name": "./SampleData/models/传感器设备/传感器设备_data/GWD100.gltf",
      "Position": "-137.25144397591,-504.804838985888,-35.7390935276022",
      "Matrix": "1,0,0,0,1,0,0,0,1"
    },
    {
      "Name": "./SampleData/models/传感器设备/传感器设备_data/GWD200.gltf",
      "Position": "-142.809178661451,-498.562376751103,-35.6234156711754",
      "Matrix": "0.8137335,0.5812382,0,-0.5812382,0.8137335,0,0,0,1"
    },
    {
      "Name": "./SampleData/models/传感器设备/传感器设备_data/GWD200.gltf",
      "Position": "-146.727257028485,-492.28893767125,-35.5237188155793",
      "Matrix": "1,0,0,0,1,0,0,0,1"
    },
    {
      "Name": "./SampleData/models/传感器设备/传感器设备_data/GWD200.gltf",
      "Position": "-159.852170908312,-479.635564354145,-35.4973626714479",
      "Matrix": "1,0,0,0,1,0,0,0,1"
    },
    {
      "Name": "./SampleData/models/传感器设备/传感器设备_data/GWD200.gltf",
      "Position": "-77.7532843049598,-562.538274858593,-36.7141899100009",
      "Matrix": "1,0,0,0,1,0,0,0,1"
    },
    {
      "Name": "./SampleData/models/传感器设备/传感器设备_data/GYH25(B).gltf",
      "Position": "-50.9113945231212,-585.508350245735,-36.9088661814606",
      "Matrix": "1,0,0,0,1,0,0,0,1"
    },
    {
      "Name": "./SampleData/models/传感器设备/传感器设备_data/GYH25(B).gltf",
      "Position": "-50.4043109061878,-584.787276377825,-36.808991579784",
      "Matrix": "1,0,0,0,1,0,0,0,1"
    },
    {
      "Name": "./SampleData/models/传感器设备/传感器设备_data/GYH25(B).gltf",
      "Position": "-48.2959383715312,-582.377803798478,-36.7355883510419",
      "Matrix": "1,0,0,0,1,0,0,0,1"
    },
    {
      "Name": "./SampleData/models/传感器设备/传感器设备_data/GYH25(B).gltf",
      "Position": "-46.8819433531421,-580.821419632666,-36.697833356818",
      "Matrix": "1,0,0,0,1,0,0,0,1"
    },
    {
      "Name": "./SampleData/models/传感器设备/传感器设备_data/GYH25(B).gltf",
      "Position": "-138.668981758591,-565.230533832295,-35.8763431033542",
      "Matrix": "0.9987524,-0.04993762,0,0.04993762,0.9987524,0,0,0,1"
    },
    {
      "Name": "./SampleData/gltf/jw.gltf",
      "Position": "-134.957575132081,-562.168205063871,-36.0588192260154",
      "Matrix": "1,0,0,0,1,0,0,0,1"
    },
    {
      "Name": "./SampleData/gltf/jw.gltf",
      "Position": "-133.101155982273,-560.526311922428,-36.106509051464",
      "Matrix": "0.9982744,-0.05872202,0,0.05872202,0.9982744,0,0,0,1"
    },
    {
      "Name": "./SampleData/gltf/jw.gltf",
      "Position": "-130.146314917321,-558.133554054356,-36.2697211239615",
      "Matrix": "1,0,0,0,1,0,0,0,1"
    },
    {
      "Name": "./SampleData/gltf/jw.gltf",
      "Position": "-129.270413939652,-557.358943576064,-36.2922508545226",
      "Matrix": "1,0,0,0,1,0,0,0,1"
    },
    {
      "Name": "./SampleData/gltf/jw.gltf",
      "Position": "-126.204197726182,-555.308498076047,-36.6327918120421",
      "Matrix": "1,0,0,0,1,0,0,0,1"
    },
    {
      "Name": "./SampleData/gltf/jw.gltf",
      "Position": "-35.736182047774,-571.86132320958,-37.8804205220645",
      "Matrix": "1,0,0,0,1,0,0,0,1"
    },
    {
      "Name": "./SampleData/gltf/jw.gltf",
      "Position": "-30.6825938224002,-574.163342754443,-36.8274602339745",
      "Matrix": "1,0,0,0,1,0,0,0,1"
    },
    {
      "Name": "./SampleData/gltf/jw.gltf",
      "Position": "-28.6640277197349,-576.320738210754,-36.8839095786728",
      "Matrix": "0.5547002,-0.8320503,0,0.8320503,0.5547002,0,0,0,1"
    },
    {
      "Name": "./SampleData/gltf/jw.gltf",
      "Position": "-26.4635534723674,-578.257653735734,-36.7695586412909",
      "Matrix": "0.7071068,-0.7071068,0,0.7071068,0.7071068,0,0,0,1"
    },
    {
      "Name": "./SampleData/gltf/jw.gltf",
      "Position": "-62.6158924854699,-589.041685588381,-37.1944204542055",
      "Matrix": "1,0,0,0,1,0,0,0,1"
    },
    {
      "Name": "./SampleData/gltf/jw.gltf",
      "Position": "-61.8938828103835,-589.190677998548,-37.1015155079403",
      "Matrix": "1,0,0,0,1,0,0,0,1"
    },
    {
      "Name": "./SampleData/gltf/jw.gltf",
      "Position": "-61.0689063279387,-589.102515003079,-36.9974831223509",
      "Matrix": "1,0,0,0,1,0,0,0,1"
    },
    {
      "Name": "./SampleData/gltf/jw.gltf",
      "Position": "-63.6045526428918,-588.247476800089,-37.3080070974298",
      "Matrix": "1,0,0,0,1,0,0,0,1"
    },
    {
      "Name": "./SampleData/gltf/jw.gltf",
      "Position": "-65.4014560984477,-587.394223974745,-37.9609116297377",
      "Matrix": "1,0,0,0,1,0,0,0,1"
    },
    {
      "Name": "./SampleData/gltf/jw.gltf",
      "Position": "-65.724875439506,-586.691855925683,-37.6116461112592",
      "Matrix": "0.2425356,0.9701425,0,-0.9701425,0.2425356,0,0,0,1"
    },
    {
      "Name": "./SampleData/gltf/jw.gltf",
      "Position": "-67.2966670880404,-584.499131597674,-37.4139441429054",
      "Matrix": "1,0,0,0,1,0,0,0,1"
    },
    {
      "Name": "./SampleData/gltf/jw.gltf",
      "Position": "-67.7243914039803,-583.974502629207,-37.3894497490159",
      "Matrix": "1,0,0,0,1,0,0,0,1"
    },
    {
      "Name": "./SampleData/gltf/jw.gltf",
      "Position": "-71.9062229732304,-579.369377287192,-37.3631247423585",
      "Matrix": "1,0,0,0,1,0,0,0,1"
    },
    {
      "Name": "./SampleData/gltf/jw.gltf",
      "Position": "-73.8156730199378,-577.127858493224,-37.2946599008448",
      "Matrix": "1,0,0,0,1,0,0,0,1"
    },
    {
      "Name": "./SampleData/gltf/jw.gltf",
      "Position": "-74.0968629698896,-576.073934868498,-37.0015271037665",
      "Matrix": "1,0,0,0,1,0,0,0,1"
    },
    {
      "Name": "./SampleData/gltf/jw.gltf",
      "Position": "-74.4593984778731,-575.467250445324,-36.973870252086",
      "Matrix": "1,0,0,0,1,0,0,0,1"
    },
    {
      "Name": "./SampleData/models/传感器设备/传感器设备_data/GTH1000.gltf",
      "Position": "-96.0895514857426,-632.07243765778,-38.8506716284827",
      "Matrix": "1,0,0,0,1,0,0,0,1"
    },
    
    {
      "Name": "./SampleData/models/传感器设备/传感器设备_data/GTH1000.gltf",
      "Position": "-97.9023962264847,-633.917925292121,-38.5410677821565",
      "Matrix": "1,0,0,0,1,0,0,0,1"
    },
    
    {
      "Name": "./SampleData/models/传感器设备/传感器设备_data/GTH1000.gltf",
      "Position": "-100.615376643431,-636.336748054377,-38.0898672028534",
      "Matrix": "1,0,0,0,1,0,0,0,1"
    },
    
    {
      "Name": "./SampleData/gltf/jw.gltf",
      "Position": "-102.515342351984,-638.148358373719,-37.96035488307",
      "Matrix": "1,0,0,0,1,0,0,0,1"
    },
    
    {
      "Name": "./SampleData/gltf/jw.gltf",
      "Position": "-103.894831202856,-639.30660161421,-37.8534954172707",
      "Matrix": "-0.9908302,-0.1351132,0,0.1351132,-0.9908302,0,0,0,1"
    },
    
    {
      "Name": "./SampleData/gltf/jw.gltf",
      "Position": "-107.024618116349,-642.248462069111,-37.7856477065931",
      "Matrix": "1,0,0,0,1,0,0,0,1"
    },
    
    {
      "Name": "./SampleData/gltf/jw.gltf",
      "Position": "-108.403599664437,-643.764708963825,-37.8495095176885",
      "Matrix": "1,0,0,0,1,0,0,0,1"
    },
    {
      "Name": "./SampleData/gltf/jw.gltf",
      "Position": "-78.3975542934058,-634.238395006162,-37.8039089911687",
      "Matrix": "0.7808688,-0.6246951,0,0.6246951,0.7808688,0,0,0,1"
    },
    
    {
      "Name": "./SampleData/gltf/jw.gltf",
      "Position": "-76.1608637537578,-633.173190862154,-37.8495443913938",
      "Matrix": "1,0,0,0,1,0,0,0,1"
    },
    
    {
      "Name": "./SampleData/gltf/jw.gltf",
      "Position": "-75.1830884109665,-632.574411564789,-37.8999827787793",
      "Matrix": "0.8137335,-0.5812382,0,0.5812382,0.8137335,0,0,0,1"
    },
    
    {
      "Name": "./SampleData/gltf/jw.gltf",
      "Position": "-74.4094036891403,-632.16038338331,-38.0057528208463",
      "Matrix": "1,0,0,0,1,0,0,0,1"
    },
    
    {
      "Name": "./SampleData/gltf/jw.gltf",
      "Position": "-74.272546384207,-632.075733927224,-38.0237218720496",
      "Matrix": "1,0,0,0,1,0,0,0,1"
    },
    
    {
      "Name": "./SampleData/gltf/jw.gltf",
      "Position": "-142.268433330216,-596.781428771614,-37.6688270910416",
      "Matrix": "1,0,0,0,1,0,0,0,1"
    },
    
    {
      "Name": "./SampleData/gltf/jw.gltf",
      "Position": "-138.578061883574,-593.255295003837,-37.1944225059835",
      "Matrix": "1,0,0,0,1,0,0,0,1"
    },
    
    {
      "Name": "./SampleData/gltf/jw.gltf",
      "Position": "-136.084511369118,-591.090030778068,-37.342133161629",
      "Matrix": "1,0,0,0,1,0,0,0,1"
    },
    
    {
      "Name": "./SampleData/gltf/jw.gltf",
      "Position": "-133.858349136156,-589.2171675753,-37.5738816695154",
      "Matrix": "0.9922779,-0.1240347,0,0.1240347,0.9922779,0,0,0,1"
    },
    
    {
      "Name": "./SampleData/models/传感器设备/传感器设备_data/GFY15.gltf",
      "Position": "-128.510350328626,-584.457537764979,-37.6987457482972",
      "Matrix": "0.961524,0.2747211,0,-0.2747211,0.961524,0,0,0,1"
    },
    
    {
      "Name": "./SampleData/models/传感器设备/传感器设备_data/GFY15.gltf",
      "Position": "-124.605348901502,-580.600851925747,-37.1566054150346",
      "Matrix": "1,0,0,0,1,0,0,0,1"
    },
    
    {
      "Name": "./SampleData/models/传感器设备/传感器设备_data/GFY15.gltf",
      "Position": "-121.945990591401,-578.233532184717,-37.2177307491239",
      "Matrix": "1,0,0,0,1,0,0,0,1"
    },
    
    {
      "Name": "./SampleData/models/传感器设备/传感器设备_data/GFY15.gltf",
      "Position": "-136.640904145625,-564.809085319781,-36.6369481592585",
      "Matrix": "1,0,0,0,1,0,0,0,1"
    },
    
    {
      "Name": "./SampleData/gltf/jw.gltf",
      "Position": "-137.977062939644,-566.275710524137,-37.0151218427395",
      "Matrix": "1,0,0,0,1,0,0,0,1"
    },
    
    {
      "Name": "./SampleData/gltf/jw.gltf",
      "Position": "-136.543282179908,-537.816091172682,-36.6206349022635",
      "Matrix": "1,0,0,0,1,0,0,0,1"
    },
    
    {
      "Name": "./SampleData/gltf/jw.gltf",
      "Position": "-134.695564022102,-538.769627489795,-36.1442394068292",
      "Matrix": "1,0,0,0,1,0,0,0,1"
    },
    
    {
      "Name": "./SampleData/gltf/jw.gltf",
      "Position": "-131.774180980665,-541.581308804311,-36.0126507390211",
      "Matrix": "0.8944272,-0.4472136,0,0.4472136,0.8944272,0,0,0,1"
    },
    
    {
      "Name": "./SampleData/gltf/jw.gltf",
      "Position": "-127.135299280059,-546.381025840563,-36.1207907308766",
      "Matrix": "0.5547002,-0.8320503,0,0.8320503,0.5547002,0,0,0,1"
    },
    
    {
      "Name": "./SampleData/gltf/jw.gltf",
      "Position": "-122.634512822613,-552.482381095896,-36.525637521553",
      "Matrix": "1,0,0,0,1,0,0,0,1"
    },
    {
      "Name": "./SampleData/models/传感器设备/传感器设备_data/GFY15.gltf",
      "Position": "-82.3872989653737,-597.971663735171,-37.5834156246901",
      "Matrix": "0.7739573,-0.6332378,0,0.6332378,0.7739573,0,0,0,1"
    },
    
    {
      "Name": "./SampleData/models/传感器设备/传感器设备_data/GFY15.gltf",
      "Position": "-80.4703344702351,-599.92292686135,-37.5136753697478",
      "Matrix": "0.8619342,-0.5070201,0,0.5070201,0.8619342,0,0,0,1"
    },
    
    {
      "Name": "./SampleData/models/传感器设备/传感器设备_data/GFY15.gltf",
      "Position": "-77.919408694793,-602.596534181778,-37.4518423679693",
      "Matrix": "0.6401844,-0.7682213,0,0.7682213,0.6401844,0,0,0,1"
    },
    
    {
      "Name": "./SampleData/models/传感器设备/传感器设备_data/GLH100.gltf",
      "Position": "-74.7124768925789,-608.536408301741,-37.0880079562004",
      "Matrix": "0.7808688,-0.6246951,0,0.6246951,0.7808688,0,0,0,1"
    },
    
    {
      "Name": "./SampleData/models/传感器设备/传感器设备_data/GLH100.gltf",
      "Position": "-73.7415863944957,-608.661704327361,-37.3831434622956",
      "Matrix": "1,0,0,0,1,0,0,0,1"
    },
    
    {
      "Name": "./SampleData/gltf/jw.gltf",
      "Position": "-72.4449875980221,-607.680547402636,-37.4998937607331",
      "Matrix": "1,0,0,0,1,0,0,0,1"
    },
    
    {
      "Name": "./SampleData/gltf/jw.gltf",
      "Position": "-72.9451810812924,-608.769096260902,-37.9675917242305",
      "Matrix": "1,0,0,0,1,0,0,0,1"
    },
    
    {
      "Name": "./SampleData/gltf/jw.gltf",
      "Position": "-80.539816117399,-640.473208136649,-38.0843287265887",
      "Matrix": "1,0,0,0,1,0,0,0,1"
    },
    
    {
      "Name": "./SampleData/gltf/jw.gltf",
      "Position": "-84.1033244911408,-644.481434860473,-38.3153884910049",
      "Matrix": "-0.961524,-0.2747211,0,0.2747211,-0.961524,0,0,0,1"
    },
    
    {
      "Name": "./SampleData/gltf/jw.gltf",
      "Position": "-87.4902323028087,-647.476516121004,-38.1751293152046",
      "Matrix": "-0.8574929,-0.5144957,0,0.5144957,-0.8574929,0,0,0,1"
    },
    
    {
      "Name": "./SampleData/gltf/jw.gltf",
      "Position": "-88.0283090999935,-648.26235671093,-38.2866942796083",
      "Matrix": "1,0,0,0,1,0,0,0,1"
    },
    
    {
      "Name": "./SampleData/gltf/jw.gltf",
      "Position": "-92.4702101237826,-627.593556749723,-37.6863626166264",
      "Matrix": "1,0,0,0,1,0,0,0,1"
    },
    
    {
      "Name": "./SampleData/gltf/jw.gltf",
      "Position": "-93.663808818557,-629.185807115371,-37.8605500597114",
      "Matrix": "1,0,0,0,1,0,0,0,1"
    },
    
    {
      "Name": "./SampleData/gltf/jw.gltf",
      "Position": "-95.666648613633,-631.039472154507,-37.8048241166541",
      "Matrix": "1,0,0,0,1,0,0,0,1"
    },
    
    {
      "Name": "./SampleData/gltf/jw.gltf",
      "Position": "-96.4841292774957,-632.066075197571,-37.8970885293431",
      "Matrix": "1,0,0,0,1,0,0,0,1"
    },
    
    {
      "Name": "./SampleData/gltf/jw.gltf",
      "Position": "-98.3673608089435,-633.737328767266,-37.8141353430909",
      "Matrix": "1,0,0,0,1,0,0,0,1"
    },
    
    {
      "Name": "./SampleData/models/传感器设备/传感器设备_data/GLH100.gltf",
      "Position": "-137.004893208769,-623.230594664306,-37.1476925178444",
      "Matrix": "1,0,0,0,1,0,0,0,1"
    },
    
    {
      "Name": "./SampleData/models/传感器设备/传感器设备_data/GLH100.gltf",
      "Position": "-139.325452556701,-625.640806892647,-37.3203298584981",
      "Matrix": "1,0,0,0,1,0,0,0,1"
    },
    
    {
      "Name": "./SampleData/gltf/jw.gltf",
      "Position": "-140.386364018752,-626.796158739509,-37.6638735748248",
      "Matrix": "1,0,0,0,1,0,0,0,1"
    },
    
    {
      "Name": "./SampleData/gltf/jw.gltf",
      "Position": "-144.565661545416,-631.024354870829,-37.6310189433735",
      "Matrix": "1,0,0,0,1,0,0,0,1"
    },
    
    {
      "Name": "./SampleData/gltf/jw.gltf",
      "Position": "-146.973912214747,-633.339277180236,-37.4992839777487",
      "Matrix": "1,0,0,0,1,0,0,0,1"
    },
    
    {
      "Name": "./SampleData/gltf/jw.gltf",
      "Position": "-148.327875428701,-634.544887207345,-37.2811745124566",
      "Matrix": "1,0,0,0,1,0,0,0,1"
    },
    
    {
      "Name": "./SampleData/gltf/jw.gltf",
      "Position": "-148.07806052912,-633.97932993371,-36.8753997954253",
      "Matrix": "1,0,0,0,1,0,0,0,1"
    },
    
    {
      "Name": "./SampleData/gltf/jw.gltf",
      "Position": "-147.25727812733,-633.013083857304,-36.8028502021818",
      "Matrix": "1,0,0,0,1,0,0,0,1"
    },
    
    {
      "Name": "./SampleData/gltf/jw.gltf",
      "Position": "-146.249193980375,-631.993071436512,-36.7854959731044",
      "Matrix": "0.9965457,0.08304548,0,-0.08304548,0.9965457,0,0,0,1"
    },
    
    {
      "Name": "./SampleData/gltf/jw.gltf",
      "Position": "-145.13733036794,-630.417021595507,-36.5722576037969",
      "Matrix": "1,0,0,0,1,0,0,0,1"
    },
    
    {
      "Name": "./SampleData/gltf/jw.gltf",
      "Position": "-143.892800430293,-628.834088042287,-36.4115405849827",
      "Matrix": "0.9990562,0.04343722,0,-0.04343722,0.9990562,0,0,0,1"
    },
    
    {
      "Name": "./SampleData/gltf/jw.gltf",
      "Position": "-142.150234631213,-627.034601695851,-36.3659201441615",
      "Matrix": "1,0,0,0,1,0,0,0,1"
    },
    
    {
      "Name": "./SampleData/gltf/jw.gltf",
      "Position": "-140.152325123347,-625.238936770295,-36.4287340650167",
      "Matrix": "1,0,0,0,1,0,0,0,1"
    },
    
    {
      "Name": "./SampleData/models/传感器设备/传感器设备_data/GLH100.gltf",
      "Position": "-138.635620575413,-623.758424595991,-36.4259222243204",
      "Matrix": "1,0,0,0,1,0,0,0,1"
    },
    
    {
      "Name": "./SampleData/models/传感器设备/传感器设备_data/GLH100.gltf",
      "Position": "-136.930556067601,-622.108172749995,-36.4288400100645",
      "Matrix": "1,0,0,0,1,0,0,0,1"
    },
    
    {
      "Name": "./SampleData/models/传感器设备/传感器设备_data/GLH100.gltf",
      "Position": "-134.542824064843,-619.607357364488,-36.3512289539993",
      "Matrix": "1,0,0,0,1,0,0,0,1"
    },
    
    {
      "Name": "./SampleData/models/传感器设备/传感器设备_data/GTH1000.gltf",
      "Position": "-132.695020096863,-617.708822746412,-36.306758435654",
      "Matrix": "1,0,0,0,1,0,0,0,1"
    },
    
    {
      "Name": "./SampleData/models/传感器设备/传感器设备_data/GTH1000.gltf",
      "Position": "-131.215210729396,-616.377477449036,-36.3529911849847",
      "Matrix": "1,0,0,0,1,0,0,0,1"
    },
    
    {
      "Name": "./SampleData/models/传感器设备/传感器设备_data/GTH1000.gltf",
      "Position": "-129.793516817065,-615.099027181687,-36.3972095484956",
      "Matrix": "1,0,0,0,1,0,0,0,1"
    },
    
    {
      "Name": "./SampleData/models/传感器设备/传感器设备_data/GLH100.gltf",
      "Position": "-129.174437694005,-614.542252869726,-36.4164876023764",
      "Matrix": "1,0,0,0,1,0,0,0,1"
    },
    
    {
      "Name": "./SampleData/models/传感器设备/传感器设备_data/GLH100.gltf",
      "Position": "-127.748277740847,-613.259623239534,-36.4608980620339",
      "Matrix": "1,0,0,0,1,0,0,0,1"
    },
    
    {
      "Name": "./SampleData/models/传感器设备/传感器设备_data/GLH100.gltf",
      "Position": "-126.499786046097,-612.017334526708,-36.4484107816535",
      "Matrix": "1,0,0,0,1,0,0,0,1"
    },
    
    {
      "Name": "./SampleData/models/传感器设备/传感器设备_data/GTH1000.gltf",
      "Position": "-125.814866129329,-611.40128188152,-36.469711661755",
      "Matrix": "0.9965457,-0.08304548,0,0.08304548,0.9965457,0,0,0,1"
    },
    
    {
      "Name": "./SampleData/gltf/jw.gltf",
      "Position": "-124.012846522565,-609.900129971266,-36.5772189677352",
      "Matrix": "1,0,0,0,1,0,0,0,1"
    },
    
    {
      "Name": "./SampleData/gltf/jw.gltf",
      "Position": "-122.825572775226,-608.831987197127,-36.6143070086482",
      "Matrix": "1,0,0,0,1,0,0,0,1"
    },
    
    {
      "Name": "./SampleData/gltf/jw.gltf",
      "Position": "-122.277073228182,-608.305543148372,-36.6421836535592",
      "Matrix": "1,0,0,0,1,0,0,0,1"
    },
    
    {
      "Name": "./SampleData/gltf/jw.gltf",
      "Position": "-121.544550937732,-607.602476021935,-36.6794129710514",
      "Matrix": "0.8320503,0.5547002,0,-0.5547002,0.8320503,0,0,0,1"
    },
    
    {
      "Name": "./SampleData/gltf/jw.gltf",
      "Position": "-120.829153820239,-606.315057150277,-36.3659022173085",
      "Matrix": "1,0,0,0,1,0,0,0,1"
    },
    
    {
      "Name": "./SampleData/models/传感器设备/传感器设备_data/GELH100.gltf",
      "Position": "-119.515446153615,-605.253539730153,-36.4584507019298",
      "Matrix": "1,0,0,0,1,0,0,0,1"
    },
    
    {
      "Name": "./SampleData/models/传感器设备/传感器设备_data/GELH100.gltf",
      "Position": "-117.045132153131,-603.046856486307,-36.5296725887164",
      "Matrix": "1,0,0,0,1,0,0,0,1"
    },
    
    {
      "Name": "./SampleData/gltf/jw.gltf",
      "Position": "-114.44827189309,-602.365433209126,-35.8972532472336",
      "Matrix": "0.9701425,0.2425356,0,-0.2425356,0.9701425,0,0,0,1"
    },
    
    {
      "Name": "./SampleData/gltf/jw.gltf",
      "Position": "-114.120867014339,-599.496333451197,-36.3665877788787",
      "Matrix": "1,0,0,0,1,0,0,0,1"
    },
    
    {
      "Name": "./SampleData/gltf/jw.gltf",
      "Position": "-110.896311987716,-596.290163059711,-36.5617623217893",
      "Matrix": "0.9863939,-0.164399,0,0.164399,0.9863939,0,0,0,1"
    },
    
    {
      "Name": "./SampleData/gltf/jw.gltf",
      "Position": "-108.297235745046,-593.963773036705,-36.8213017121363",
      "Matrix": "1,0,0,0,1,0,0,0,1"
    },
    
    {
      "Name": "./SampleData/gltf/jw.gltf",
      "Position": "-106.914359822991,-592.589143764598,-36.9052730977616",
      "Matrix": "0.9987524,-0.04993762,0,0.04993762,0.9987524,0,0,0,1"
    },
    
    {
      "Name": "./SampleData/gltf/jw.gltf",
      "Position": "-104.592201109109,-590.410416504812,-37.0975302143282",
      "Matrix": "1,0,0,0,1,0,0,0,1"
    },
    
    {
      "Name": "./SampleData/models/传感器设备/传感器设备_data/GELH100.gltf",
      "Position": "-102.712982061245,-588.282712298233,-37.1089325327588",
      "Matrix": "0.9995121,-0.03123475,0,0.03123475,0.9995121,0,0,0,1"
    },
    
    {
      "Name": "./SampleData/models/传感器设备/传感器设备_data/GELH100.gltf",
      "Position": "-105.173675728216,-542.190264616552,-50",
      "Matrix": "1,0,0,0,1,0,0,0,1"
    },
    
    {
      "Name": "./SampleData/gltf/jw.gltf",
      "Position": "-99.1925185369966,-577.688515212353,-37.0443100480718",
      "Matrix": "1,0,0,0,1,0,0,0,1"
    },
    
    {
      "Name": "./SampleData/models/传感器设备/传感器设备_data/GFY15.gltf",
      "Position": "-102.768007366497,-574.561900579572,-37.139725314352",
      "Matrix": "1,0,0,0,1,0,0,0,1"
    },
    
    {
      "Name": "./SampleData/models/传感器设备/传感器设备_data/GFY15.gltf",
      "Position": "-104.516688760805,-572.467160962048,-37.030005067251",
      "Matrix": "1,0,0,0,1,0,0,0,1"
    },
    
    {
      "Name": "./SampleData/models/传感器设备/传感器设备_data/GFY15.gltf",
      "Position": "-106.797872571211,-569.688032562228,-36.869402381465",
      "Matrix": "-0.7592566,0.6507913,0,-0.6507913,-0.7592566,0,0,0,1"
    },
    
    {
      "Name": "./SampleData/models/传感器设备/传感器设备_data/GFY15.gltf",
      "Position": "-111.057520476202,-566.897061959142,-36.7347480419424",
      "Matrix": "1,0,0,0,1,0,0,0,1"
    },
    
    {
      "Name": "./SampleData/gltf/jw.gltf",
      "Position": "-115.133593762609,-561.604289595084,-37.0615488683757",
      "Matrix": "-0.7432941,0.6689647,0,-0.6689647,-0.7432941,0,0,0,1"
    },
    
    {
      "Name": "./SampleData/gltf/jw.gltf",
      "Position": "-123.663057588937,-553.114235665653,-36.8037941932655",
      "Matrix": "1,0,0,0,1,0,0,0,1"
    },
    
    {
      "Name": "./SampleData/gltf/jw.gltf",
      "Position": "-130.680041197731,-514.468559287667,-36.6191636794265",
      "Matrix": "1,0,0,0,1,0,0,0,1"
    },
    
    {
      "Name": "./SampleData/gltf/jw.gltf",
      "Position": "-123.440374914564,-521.303713998205,-36.1948509382305",
      "Matrix": "1,0,0,0,1,0,0,0,1"
    },
    
    {
      "Name": "./SampleData/gltf/jw.gltf",
      "Position": "-118.866190601782,-527.362205889239,-36.6527710298489",
      "Matrix": "1,0,0,0,1,0,0,0,1"
    },
    
    {
      "Name": "./SampleData/gltf/jw.gltf",
      "Position": "-114.066462586047,-532.941177284034,-36.8589333695764",
      "Matrix": "0.955779,-0.2940859,0,0.2940859,0.955779,0,0,0,1"
    },
    
    {
      "Name": "./SampleData/gltf/jw.gltf",
      "Position": "-108.046027426449,-537.032710792874,-36.2837933968333",
      "Matrix": "0.7071068,-0.7071068,0,0.7071068,0.7071068,0,0,0,1"
    },
    
    {
      "Name": "./SampleData/gltf/jw.gltf",
      "Position": "-105.012747262547,-541.828762526135,-36.5489089005437",
      "Matrix": "0.7474093,-0.6643639,0,0.6643639,0.7474093,0,0,0,1"
    },
    
    {
      "Name": "./SampleData/models/传感器设备/传感器设备_data/GELH100.gltf",
      "Position": "-100.886891205518,-546.43532798497,-36.6324496296158",
      "Matrix": "0.7071068,-0.7071068,0,0.7071068,0.7071068,0,0,0,1"
    },
    
    {
      "Name": "./SampleData/models/传感器设备/传感器设备_data/GELH100.gltf",
      "Position": "-95.9887101847063,-552.733694549758,-37.0504336339337",
      "Matrix": "0.8411785,-0.5407576,0,0.5407576,0.8411785,0,0,0,1"
    },
    
    {
      "Name": "./SampleData/models/传感器设备/传感器设备_data/GELH100.gltf",
      "Position": "-91.682905191369,-557.288386038281,-37.0404615377905",
      "Matrix": "0.7808688,-0.6246951,0,0.6246951,0.7808688,0,0,0,1"
    },
    
    {
      "Name": "./SampleData/gltf/jw.gltf",
      "Position": "-89.8431754205887,-559.52491155711,-37.1478335860407",
      "Matrix": "0.9429904,-0.3328201,0,0.3328201,0.9429904,0,0,0,1"
    },
    
    {
      "Name": "./SampleData/gltf/jw.gltf",
      "Position": "-84.1576038184305,-567.18337349394,-36.666604846808",
      "Matrix": "0.8454889,-0.533993,0,0.533993,0.8454889,0,0,0,1"
    },
    
    {
      "Name": "./SampleData/gltf/jw.gltf",
      "Position": "-80.8158382518342,-569.390819056098,-37.2389645130092",
      "Matrix": "0.919145,-0.3939193,0,0.3939193,0.919145,0,0,0,1"
    },
    
    {
      "Name": "./SampleData/gltf/jw.gltf",
      "Position": "-78.7056898895429,-571.579822551836,-37.197522087049",
      "Matrix": "0.7682213,-0.6401844,0,0.6401844,0.7682213,0,0,0,1"
    },
    
    {
      "Name": "./SampleData/models/传感器设备/传感器设备_data/GLH100.gltf",
      "Position": "-76.5233199822877,-574.065474578801,-37.2447814517039",
      "Matrix": "1,0,0,0,1,0,0,0,1"
    },
    
    {
      "Name": "./SampleData/models/传感器设备/传感器设备_data/GLH100.gltf",
      "Position": "-76.5233199822877,-574.065474578801,-37.2447814517039",
      "Matrix": "1,0,0,0,1,0,0,0,1"
    },
    
    {
      "Name": "./SampleData/models/传感器设备/传感器设备_data/GLH100.gltf",
      "Position": "-76.4889335977569,-574.193994023544,-37.2818437099823",
      "Matrix": "1,0,0,0,1,0,0,0,1"
    },
    
    {
      "Name": "./SampleData/gltf/jw.gltf",
      "Position": "-77.2279990637855,-603.85320987384,-37.6489585154162",
      "Matrix": "1,0,0,0,1,0,0,0,1"
    },
    
    {
      "Name": "./SampleData/gltf/jw.gltf",
      "Position": "-76.5840288051398,-603.916510748981,-37.387463114376",
      "Matrix": "1,0,0,0,1,0,0,0,1"
    },
    
    {
      "Name": "./SampleData/gltf/jw.gltf",
      "Position": "-73.8292056383642,-634.296229038971,-38.7159936629862",
      "Matrix": "1,0,0,0,1,0,0,0,1"
    },
    
    {
      "Name": "./SampleData/models/传感器设备/传感器设备_data/GELH100.gltf",
      "Position": "-75.6279296951347,-636.200974824542,-38.7011842681982",
      "Matrix": "-0.9363292,-0.3511235,0,0.3511235,-0.9363292,0,0,0,1"
    },
    
    {
      "Name": "./SampleData/models/传感器设备/传感器设备_data/GELH100.gltf",
      "Position": "-77.8428292841392,-638.494002250419,-38.643269602933",
      "Matrix": "-1,1.224647E-16,0,-1.224647E-16,-1,0,0,0,1"
    },
    
    {
      "Name": "./SampleData/gltf/jw.gltf",
      "Position": "-79.9539598403995,-639.470248137158,-37.899445236575",
      "Matrix": "1,0,0,0,1,0,0,0,1"
    },
    
    {
      "Name": "./SampleData/gltf/jw.gltf",
      "Position": "-81.2489829373892,-637.392274793633,-37.6490045342931",
      "Matrix": "1,0,0,0,1,0,0,0,1"
    },
    
    {
      "Name": "./SampleData/gltf/jw.gltf",
      "Position": "-83.9598981685561,-634.082472626975,-37.5446032308658",
      "Matrix": "1,0,0,0,1,0,0,0,1"
    },
    
    {
      "Name": "./SampleData/gltf/jw.gltf",
      "Position": "-85.08027572013,-633.175548530613,-37.5811278113698",
      "Matrix": "1,0,0,0,1,0,0,0,1"
    },
    
    {
      "Name": "./SampleData/gltf/jw.gltf",
      "Position": "-87.5002043792838,-631.388729856925,-37.7374959970792",
      "Matrix": "1,0,0,0,1,0,0,0,1"
    },
    
    {
      "Name": "./SampleData/gltf/jw.gltf",
      "Position": "-88.3762498689498,-630.420191947532,-37.6491135720215",
      "Matrix": "1,0,0,0,1,0,0,0,1"
    },
    
    {
      "Name": "./SampleData/gltf/jw.gltf",
      "Position": "-91.6349760136726,-626.963166199598,-37.3785963524753",
      "Matrix": "1,0,0,0,1,0,0,0,1"
    },
    
    {
      "Name": "./SampleData/gltf/jw.gltf",
      "Position": "-92.8453456154195,-625.628171425559,-37.1734290129477",
      "Matrix": "1,0,0,0,1,0,0,0,1"
    },
    
    {
      "Name": "./SampleData/gltf/jw.gltf",
      "Position": "-94.8283139321448,-623.161919453166,-37.009493011517",
      "Matrix": "1,0,0,0,1,0,0,0,1"
    },
    
    {
      "Name": "./SampleData/gltf/jw.gltf",
      "Position": "-98.3076440784389,-620.462995522686,-37.1075554849199",
      "Matrix": "1,0,0,0,1,0,0,0,1"
    },
    {
      "Name": "./SampleData/gltf/jw.gltf",
      "Position": "-98.9787505518846,-619.826296782374,-37.0872916578754",
      "Matrix": "1,0,0,0,1,0,0,0,1"
    },
    {
      "Name": "./SampleData/gltf/jw.gltf",
      "Position": "-209.229722793835,-627.362138159863,-35.9180040050563",
      "Matrix": "1,0,0,0,1,0,0,0,1"
    }
  ]
}